cryptatools_core/python3_bindings.py
cryptatools_core/uniffi_cryptatools.dll
cryptatools_core/cryptography/encryption/monoalphabetic_cipher/caesar_number.py
cryptatools_core/cryptography/encryption/transpositional_ciphers/columnar_transposition.py
cryptatools_core/utils/alphabets.py
cryptatools_python3-0.1.15.dist-info/METADATA
cryptatools_python3-0.1.15.dist-info/WHEEL
cryptatools_python3-0.1.15.dist-info/top_level.txt
cryptatools_python3-0.1.15.dist-info/RECORD
